tailwind_processor/__init__.py
tailwind_processor/tailwind_processor.py
tailwind_processor/resources/__init__.py
tailwind_processor/resources/config.js
tailwind_processor-2.0.1.dist-info/METADATA
tailwind_processor-2.0.1.dist-info/WHEEL
tailwind_processor-2.0.1.dist-info/top_level.txt
tailwind_processor-2.0.1.dist-info/RECORD
