Metadata-Version: 2.4
Name: tailwind-processor
Version: 2.0.1
Summary: Tailwind CSS classes processor
Requires-Python: >=3.9
Requires-Dist: pytailwindcss>=0.2.0
